[{"line":"参差荇菜，左右流之","poemId":"poem_0"},{"line":"窈窕淑女，寤寐求之","poemId":"poem_0"},{"line":"参差荇菜，左右采之","poemId":"poem_0"},{"line":"窈窕淑女，琴瑟友之","poemId":"poem_0"},{"line":"参差荇菜，左右芼之","poemId":"poem_0"},{"line":"窈窕淑女，钟鼓乐之","poemId":"poem_0"},{"line":"一苇杭之","poemId":"poem_16"},{"line":"跂予望之","poemId":"poem_16"},{"line":"人靡不有初，想君能终之","poemId":"poem_40"},{"line":"几行归塞尽，念尔独何之","poemId":"poem_417"},{"line":"茫茫江汉上，日暮欲何之","poemId":"poem_435"},{"line":"下马饮君酒，问君何所之","poemId":"poem_500"},{"line":"乃作歌以长之","poemId":"poem_528"},{"line":"道路阻且长，会面安可知","poemId":"poem_22"},{"line":"竹外桃花三两枝，春江水暖鸭先知","poemId":"poem_119"},{"line":"律回岁晚冰霜少，春到人间草木知","poemId":"poem_175"},{"line":"不因送客东城去，过却春光总不知","poemId":"poem_203"},{"line":"兴来每独往，胜事空自知","poemId":"poem_362"},{"line":"天涯占梦数，疑误有新知","poemId":"poem_382"},{"line":"独立三边静，轻生一剑知","poemId":"poem_435"},{"line":"汉文有道恩犹薄，湘水无情吊岂知","poemId":"poem_485"},{"line":"临别殷勤重寄词，词中有誓两心知","poemId":"poem_526"},{"line":"胡马依北风，越鸟巢南枝","poemId":"poem_22"},{"line":"上马不捉鞭，反折杨柳枝","poemId":"poem_73"},{"line":"野凫眠岸有闲意，老树着花无丑枝","poemId":"poem_93"},{"line":"荷尽已无擎雨盖，菊残犹有傲霜枝","poemId":"poem_124"},{"line":"有情芍药含春泪，无力蔷薇卧晓枝","poemId":"poem_134"},{"line":"红豆生南国，春来发几枝","poemId":"poem_283"},{"line":"碧阑干外绣帘垂，猩血屏风画折枝","poemId":"poem_368"},{"line":"客去波平槛，蝉休露满枝","poemId":"poem_382"},{"line":"燕草如碧丝，秦桑低绿枝","poemId":"poem_499"},{"line":"在天愿作比翼鸟，在地愿为连理枝","poemId":"poem_526"},{"line":"花开堪折直须折，莫待无花空折枝","poemId":"poem_588"},{"line":"（版本一）煮豆持作羹，漉菽以为汁","poemId":"poem_35"},{"line":"控弦破左的，右发摧月支","poemId":"poem_38"},{"line":"弄儿床前戏，看妇机中织","poemId":"poem_53"},{"line":"孤灯暧不明，寒机晓犹织","poemId":"poem_62"},{"line":"春寒赐浴华清池，温泉水滑洗凝脂","poemId":"poem_526"},{"line":"愿书万本诵万遍，口角流沫右手胝","poemId":"poem_536"}]